geoparticle/__init__.py
geoparticle/base.py
geoparticle/ops.py
geoparticle/shapes.py
geoparticle/utils.py
geoparticle-1.0.2.dist-info/licenses/LICENSE
geoparticle-1.0.2.dist-info/METADATA
geoparticle-1.0.2.dist-info/WHEEL
geoparticle-1.0.2.dist-info/top_level.txt
geoparticle-1.0.2.dist-info/RECORD
