Metadata-Version: 2.4
Name: geoparticle
Version: 1.0.2
Summary: geoparticle 1.0.2
Author-email: Hong Zhu <hzhu1@stu.suda.edu.cn>
Maintainer-email: Hong Zhu <hzhu1@stu.suda.edu.cn>
License: Apache-2.0
Project-URL: Homepage, https://github.com/Jasmine969/GeomParticle
Keywords: Geometry,Particle,Smoothed Particle Hydrodynamics,SPH
Requires-Python: >=3.9
License-File: LICENSE
Requires-Dist: numpy
Requires-Dist: scipy
Requires-Dist: matplotlib
Dynamic: license-file
